nemuru_ml/__init__.py
nemuru_ml/common/__init__.py
nemuru_ml/common/database_client.py
nemuru_ml/common/file_client.py
nemuru_ml/common/logger.py
nemuru_ml/common/model_registry.py
nemuru_ml/infrastructure/__init__.py
nemuru_ml/infrastructure/database/__init__.py
nemuru_ml/infrastructure/database/big_query/__init__.py
nemuru_ml/infrastructure/database/big_query/bigquery_client.py
nemuru_ml/infrastructure/file_system/__init__.py
nemuru_ml/infrastructure/file_system/pandas/__init__.py
nemuru_ml/infrastructure/file_system/pandas/pandas_reader.py
nemuru_ml/infrastructure/logger/__init__.py
nemuru_ml/infrastructure/logger/mlflow/__init__.py
nemuru_ml/infrastructure/logger/mlflow/mlflow_logger.py
nemuru_ml/infrastructure/model_registry/__init__.py
nemuru_ml/infrastructure/model_registry/mlflow/__init__.py
nemuru_ml/infrastructure/model_registry/mlflow/mlflow_registry.py
nemuru_ml/infrastructure/pipeline/__init__.py
nemuru_ml/infrastructure/pipeline/mlflow/__init__.py
nemuru_ml/infrastructure/pipeline/mlflow/mlflow_pipeline.py
nemuru_ml/pipeline/__init__.py
nemuru_ml/pipeline/pipeline.py
nemuru_ml/stages/__init__.py
nemuru_ml/stages/etl/__init__.py
nemuru_ml/stages/etl/etl.py
nemuru_ml/stages/evaluation/__init__.py
nemuru_ml/stages/evaluation/evaluation.py
nemuru_ml/stages/feature_engineering/__init__.py
nemuru_ml/stages/feature_engineering/feature_engineering.py
nemuru_ml/stages/training/__init__.py
nemuru_ml/stages/training/training.py
nemuru_ml-0.0.10.dist-info/METADATA
nemuru_ml-0.0.10.dist-info/WHEEL
nemuru_ml-0.0.10.dist-info/top_level.txt
nemuru_ml-0.0.10.dist-info/RECORD
