Metadata-Version: 2.1
Name: nemuru-ml
Version: 0.0.10
Summary: Nemuru ML core library
Home-page: UNKNOWN
Author: Nemuru
License: MIT
Platform: UNKNOWN
Classifier: Programming Language :: Python :: 3
Classifier: License :: OSI Approved :: MIT License
Classifier: Operating System :: OS Independent
Requires-Python: >=3.7
Requires-Dist: pandas (~=1.3.1)
